{
  "indexes": [
    {
      "collectionGroup": "orders",
      "queryScope": "COLLECTION",
      "fields": [
        {
          "fieldPath": "userId",
          "order": "ASCENDING"
        },
        {
          "fieldPath": "createdAt",
          "order": "DESCENDING"
        }
      ]
    },
    {
      "collectionGroup": "orders",
      "queryScope": "COLLECTION",
      "fields": [
        {
          "fieldPath": "status",
          "order": "ASCENDING"
        },
        {
          "fieldPath": "createdAt",
          "order": "DESCENDING"
        }
      ]
    },
    {
      "collectionGroup": "userSearchIndex",
      "queryScope": "COLLECTION",
      "fields": [
        {
          "fieldPath": "searchTerms",
          "arrayConfig": "CONTAINS"
        },
        {
          "fieldPath": "isActive",
          "order": "ASCENDING"
        },
        {
          "fieldPath": "displayName",
          "order": "ASCENDING"
        }
      ]
    },
    {
      "collectionGroup": "userSearchIndex",
      "queryScope": "COLLECTION",
      "fields": [
        {
          "fieldPath": "searchTerms",
          "arrayConfig": "CONTAINS"
        },
        {
          "fieldPath": "isAdmin",
          "order": "ASCENDING"
        },
        {
          "fieldPath": "displayName",
          "order": "ASCENDING"
        }
      ]
    },
    {
      "collectionGroup": "userSearchIndex",
      "queryScope": "COLLECTION",
      "fields": [
        {
          "fieldPath": "searchTerms",
          "arrayConfig": "CONTAINS"
        },
        {
          "fieldPath": "isActive",
          "order": "ASCENDING"
        },
        {
          "fieldPath": "isAdmin",
          "order": "ASCENDING"
        },
        {
          "fieldPath": "displayName",
          "order": "ASCENDING"
        }
      ]
    },
    {
      "collectionGroup": "products",
      "queryScope": "COLLECTION",
      "fields": [
        {
          "fieldPath": "isPreOrder",
          "order": "ASCENDING"
        },
        {
          "fieldPath": "preOrderStock",
          "order": "ASCENDING"
        }
      ]
    },
    {
      "collectionGroup": "products",
      "queryScope": "COLLECTION",
      "fields": [
        {
          "fieldPath": "isPreOrder",
          "order": "ASCENDING"
        },
        {
          "fieldPath": "preOrderStartDate",
          "order": "ASCENDING"
        },
        {
          "fieldPath": "preOrderEndDate",
          "order": "ASCENDING"
        }
      ]
    },
    {
      "collectionGroup": "categories",
      "queryScope": "COLLECTION",
      "fields": [
        {
          "fieldPath": "parentId",
          "order": "ASCENDING"
        },
        {
          "fieldPath": "name",
          "order": "ASCENDING"
        }
      ]
    }
  ],
  "fieldOverrides": []
}